{
  "project_info": {
    "project_number": "583886086011",
    "project_id": "chatonlineflutter-beba8",
    "storage_bucket": "chatonlineflutter-beba8.appspot.com"
  },
  "client": [
    {
      "client_info": {
        "mobilesdk_app_id": "1:583886086011:android:fc97ad4a374ddbf59767de",
        "android_client_info": {
          "package_name": "com.example.chat_flutter_firebase"
        }
      },
      "oauth_client": [
        {
          "client_id": "583886086011-sh0pft9gv3fec407t3lpj5cfl28pqs02.apps.googleusercontent.com",
          "client_type": 1,
          "android_info": {
            "package_name": "com.example.chat_flutter_firebase",
            "certificate_hash": "827e814be3f52590d16f5e25d150e9622fe3d617"
          }
        },
        {
          "client_id": "583886086011-daov1c9pkuvehug3nj7570vgd605895m.apps.googleusercontent.com",
          "client_type": 3
        }
      ],
      "api_key": [
        {
          "current_key": "AIzaSyBrqhs03GDr9oB4XXc0-9TjcVGN0NCNU4o"
        }
      ],
      "services": {
        "appinvite_service": {
          "other_platform_oauth_client": [
            {
              "client_id": "583886086011-daov1c9pkuvehug3nj7570vgd605895m.apps.googleusercontent.com",
              "client_type": 3
            }
          ]
        }
      }
    }
  ],
  "configuration_version": "1"
}